LICENSE
MANIFEST.in
README.md
setup.py
iftaixpath/IFTBOM.py
iftaixpath/IFTBase.py
iftaixpath/IFTMachine.py
iftaixpath/IFTMachiningFeature.py
iftaixpath/IFTMachiningPart.py
iftaixpath/IFTOperation.py
iftaixpath/IFTPDF.py
iftaixpath/IFTPmi.py
iftaixpath/IFTTool.py
iftaixpath/__init__.py
iftaixpath.egg-info/PKG-INFO
iftaixpath.egg-info/SOURCES.txt
iftaixpath.egg-info/dependency_links.txt
iftaixpath.egg-info/requires.txt
iftaixpath.egg-info/top_level.txt
iftaixpath/build/cut_number_0.csv
iftaixpath/build/intersection_points_0.csv
iftaixpath/build/points_of_ipw_0.csv
iftaixpath/build/toolpath_points_0.csv
iftaixpath/static/A4_template_cam_setup.prt
iftaixpath/static/A4_template_part.prt
iftaixpath/static/configuration.json
iftaixpath/static/featuretypes.txt
iftaixpath/static/tool_ug_type_map.json