Metadata-Version: 2.1
Name: iftaixpath
Version: 0.0.2
Summary: IFT-DBMS PyPi Version
Home-page: https://git.ift.tuwien.ac.at/lab/ift/sis/data-science/nxopen-export/-/tree/lea?ref_type=heads
Author-email: julian.zulehner@gmail.com
Classifier: Programming Language :: Python :: 3
Classifier: License :: OSI Approved :: MIT License
Classifier: Operating System :: OS Independent
Requires-Python: >=3.10
License-File: LICENSE
